lexicon.py
simple_game_of_life.py
simple_game_of_life-0.1.3.3.dist-info/LICENSE.txt
simple_game_of_life-0.1.3.3.dist-info/METADATA
simple_game_of_life-0.1.3.3.dist-info/WHEEL
simple_game_of_life-0.1.3.3.dist-info/top_level.txt
simple_game_of_life-0.1.3.3.dist-info/RECORD
