Metadata-Version: 2.1
Name: simple-game-of-life
Version: 0.1.3.3
Summary: Conway's game of life in python
Home-page: UNKNOWN
Author: harpie (Dorian MB)
Author-email: <dorian.mariani@gmail.com>
License: UNKNOWN
Platform: UNKNOWN
Classifier: Programming Language :: Python :: 3
Classifier: Programming Language :: Python :: 3.8
Classifier: Programming Language :: Python :: 3.9
Classifier: Programming Language :: Python :: 3.10
Classifier: License :: OSI Approved :: MIT License
Classifier: Operating System :: OS Independent
License-File: LICENSE.txt
Requires-Dist: numpy
Requires-Dist: matplotlib
